{
  "id": 136776275,
  "length": "0:18",
  "featured": "",
  "name": "Ariamacina",
  "author": "Rosie",
  "tags": "Wave",
  "enjoyment": "5.6",
  "notes": "best gameplay nEVER??",
  "creators": [
    "Rosie"
  ],
  "verifier": "markehl",
  "verification": "https://youtu.be/EX_EiG_YaFQ",
  "records": [
    {
      "user": "lrexx",
      "link": "",
      "percent": 100,
      "hz": 0
    },
    {
      "user": "nuller",
      "link": "",
      "percent": 100,
      "hz": 0
    },
    {
      "user": "Toupeurvibreur",
      "link": "",
      "percent": 100,
      "hz": 0
    },
    {
      "user": "mold",
      "link": "",
      "percent": 100,
      "hz": 0
    },
    {
      "user": "Aspect",
      "link": "",
      "percent": 100,
      "hz": 0
    }
  ],
  "nong": ""
}